LICENSE
README.md
setup.cfg
setup.py
PyCST.egg-info/PKG-INFO
PyCST.egg-info/SOURCES.txt
PyCST.egg-info/dependency_links.txt
PyCST.egg-info/requires.txt
PyCST.egg-info/top_level.txt
pycst/__init__.py
pycst/home.py
pycst/material.py
pycst/model.py
pycst/post_process.py
pycst/session.py
pycst/simulation.py