Metadata-Version: 1.1
Name: PyCST
Version: 0.0.1
Summary: Python interface to the CST
Home-page: https://github.com/Yates1011/PyCST
Author: William Yates
Author-email: william.yates4@gmail.com
License: UNKNOWN
Platform: UNKNOWN
Classifier: Development Status :: 3 - Alpha
Classifier: License :: OSI Approved :: Apache Software License
Classifier: Natural Language :: English
Classifier: Intended Audience :: Developers
Classifier: Topic :: Scientific/Engineering :: Mathematics
Classifier: Operating System :: OS Independent
Classifier: Programming Language :: Python
